shelldoc/__init__.py
shelldoc/_version.py
shelldoc/shelldoc.py
shelldoc/google_style/__init__.py
shelldoc/google_style/bashdoc.py
shelldoc/google_style/lexer.py
shelldoc/google_style/parser.py
shelldoc-0.0.2.dist-info/METADATA
shelldoc-0.0.2.dist-info/WHEEL
shelldoc-0.0.2.dist-info/entry_points.txt
shelldoc-0.0.2.dist-info/top_level.txt
shelldoc-0.0.2.dist-info/RECORD
