Metadata-Version: 2.1
Name: shelldoc
Version: 0.0.2
Summary: Google syle shell documentation generator tool
Home-page: https://github.com/antscloud/shelldoc.git
Author: Antoine Gibek
Project-URL: Bug Tracker, https://github.com/antscloud/shelldoc.git
Classifier: Programming Language :: Python :: 3
Classifier: License :: OSI Approved :: MIT License
Classifier: Operating System :: OS Independent
Requires-Python: >=3
